nerfviewer/__init__.py
nerfviewer/_frontend.py
nerfviewer/_version.py
nerfviewer/example.py
nerfviewer/labextension/build_log.json
nerfviewer/labextension/package.json
nerfviewer/labextension/static/lib_index_js.df2f72673d05482f333f.js
nerfviewer/labextension/static/lib_index_js.df2f72673d05482f333f.js.map
nerfviewer/labextension/static/lib_plugin_js.17475631cbb159227f82.js
nerfviewer/labextension/static/lib_plugin_js.17475631cbb159227f82.js.map
nerfviewer/labextension/static/lib_widget_js.98c9f7398b51e815b014.js
nerfviewer/labextension/static/lib_widget_js.98c9f7398b51e815b014.js.map
nerfviewer/labextension/static/node_modules_babel_runtime_helpers_esm_extends_js-node_modules_emotion_memoize_dist_emotion-m-00c0260.aec613fe6ae153113506.js
nerfviewer/labextension/static/node_modules_babel_runtime_helpers_esm_extends_js-node_modules_emotion_memoize_dist_emotion-m-00c0260.aec613fe6ae153113506.js.map
nerfviewer/labextension/static/node_modules_babel_runtime_helpers_esm_extends_js-node_modules_emotion_memoize_dist_emotion-m-00c0261.c01071e887095ab285d6.js
nerfviewer/labextension/static/node_modules_babel_runtime_helpers_esm_extends_js-node_modules_emotion_memoize_dist_emotion-m-00c0261.c01071e887095ab285d6.js.map
nerfviewer/labextension/static/node_modules_babel_runtime_helpers_esm_extends_js.e6015c0ca2ee0ea926a3.js
nerfviewer/labextension/static/node_modules_babel_runtime_helpers_esm_extends_js.e6015c0ca2ee0ea926a3.js.map
nerfviewer/labextension/static/remoteEntry.48691d425783e9997b98.js
nerfviewer/labextension/static/remoteEntry.48691d425783e9997b98.js.map
nerfviewer/labextension/static/remoteEntry.d64e09aab3939dc35a3b.js.map
nerfviewer/labextension/static/style.js
nerfviewer/labextension/static/vendors-node_modules_babel_runtime_helpers_esm_extends_js-node_modules_babel_runtime_helpers_-0b1751.7caf065b4e29fa99f39a.js
nerfviewer-0.1.0.dev0.dist-info/LICENSE.txt
nerfviewer-0.1.0.dev0.dist-info/METADATA
nerfviewer-0.1.0.dev0.dist-info/WHEEL
nerfviewer-0.1.0.dev0.dist-info/top_level.txt
nerfviewer-0.1.0.dev0.dist-info/RECORD
